deepdrivemd/__init__.py
deepdrivemd/config.py
deepdrivemd/deepdrivemd.py
deepdrivemd/utils.py
deepdrivemd/agents/__init__.py
deepdrivemd/agents/lof/__init__.py
deepdrivemd/agents/lof/config.py
deepdrivemd/agents/lof/lof.py
deepdrivemd/aggregation/__init__.py
deepdrivemd/aggregation/basic/__init__.py
deepdrivemd/aggregation/basic/aggregate.py
deepdrivemd/aggregation/basic/config.py
deepdrivemd/data/__init__.py
deepdrivemd/data/analysis.py
deepdrivemd/data/api.py
deepdrivemd/data/utils.py
deepdrivemd/models/__init__.py
deepdrivemd/models/aae/__init__.py
deepdrivemd/models/aae/config.py
deepdrivemd/models/aae/inference.py
deepdrivemd/models/aae/train.py
deepdrivemd/models/keras_cvae/__init__.py
deepdrivemd/models/keras_cvae/config.py
deepdrivemd/models/keras_cvae/inference.py
deepdrivemd/models/keras_cvae/model.py
deepdrivemd/models/keras_cvae/train.py
deepdrivemd/models/keras_cvae/utils.py
deepdrivemd/selection/__init__.py
deepdrivemd/selection/latest/__init__.py
deepdrivemd/selection/latest/config.py
deepdrivemd/selection/latest/select_model.py
deepdrivemd/sim/__init__.py
deepdrivemd/sim/openmm/__init__.py
deepdrivemd/sim/openmm/config.py
deepdrivemd/sim/openmm/run_openmm.py
deepdrivemd-0.0.1.dist-info/LICENSE.md
deepdrivemd-0.0.1.dist-info/METADATA
deepdrivemd-0.0.1.dist-info/WHEEL
deepdrivemd-0.0.1.dist-info/top_level.txt
deepdrivemd-0.0.1.dist-info/RECORD
