Metadata-Version: 2.1
Name: deepdrivemd
Version: 0.0.1
Summary: Deep-Learning Driven Adaptive Molecular Simulations
Home-page: https://deepdrivemd.github.io/
Author: Alexander Brace, Hyungro Lee, Heng Ma, Anda Trifan, Matteo Turilli, Igor Yakushin, Li Tan, Andre Merzky, Tod Munson, Ian Foster, Shantenu Jha, Arvind Ramanathan
Author-email: ramanathana@anl.gov, shantenu.jha@rutgers.edu
License: MIT License
Keywords: workflow,machine-learning,complex-biological-systems,multi-scale-molecular-simulations
Platform: UNKNOWN
Classifier: Programming Language :: Python :: 3
Classifier: License :: OSI Approved :: MIT License
Classifier: Operating System :: POSIX :: Linux
Classifier: Topic :: Scientific/Engineering :: Artificial Intelligence
Classifier: Topic :: Scientific/Engineering :: Physics
Requires-Python: >=3.6
Requires-Dist: pyyaml
Requires-Dist: pydantic
Requires-Dist: radical.entk
Requires-Dist: MDAnalysis
Requires-Dist: numpy
Requires-Dist: h5py (==2.10.0)
